jaison_grpc/__init__.py
jaison_grpc/client.py
jaison_grpc/common.py
jaison_grpc/server.py
jaison_grpc/grpc/jaisongrpc_pb2.py
jaison_grpc/grpc/jaisongrpc_pb2.pyi
jaison_grpc/grpc/jaisongrpc_pb2_grpc.py
jaison_grpc-1.1.5.dist-info/METADATA
jaison_grpc-1.1.5.dist-info/WHEEL
jaison_grpc-1.1.5.dist-info/licenses/LICENSE
jaison_grpc-1.1.5.dist-info/RECORD
