Metadata-Version: 2.4
Name: jaison-grpc
Version: 1.1.5
Summary: Reusable GRPC for Project J.A.I.son components
Project-URL: documentation, https://github.com/limitcantcode/jaison-grpc
Project-URL: repository, https://github.com/limitcantcode/jaison-grpc
Author: Limit Can't Code
Author-email: limit@limit-cc.com
Maintainer-email: Limit <limit@limit-cc.com>
License: MIT License
License-File: LICENSE
Keywords: grpc,jaison
Classifier: Operating System :: OS Independent
Classifier: Programming Language :: Python
Requires-Python: >=3.9
Requires-Dist: grpcio-tools==1.68.1
Requires-Dist: grpcio==1.68.1
